personality_questionnaire/__init__.py
personality_questionnaire/api.py
personality_questionnaire/bfi2.py
personality_questionnaire/io.py
personality_questionnaire/vasf.py
personality_questionnaire-1.1.2.dist-info/METADATA
personality_questionnaire-1.1.2.dist-info/WHEEL
personality_questionnaire-1.1.2.dist-info/entry_points.txt
personality_questionnaire-1.1.2.dist-info/licenses/LICENSE
personality_questionnaire-1.1.2.dist-info/RECORD
