Metadata-Version: 2.1
Name: personality_questionnaire
Version: 1.1.2
Summary: Personality and general experiment questionnaire processing methods.
Project-URL: Documentation, https://github.com/fodorad/personality_questionnaire#readme
Project-URL: Issues, https://github.com/fodorad/personality_questionnaire/issues
Project-URL: Source, https://github.com/fodorad/personality_questionnaire
Author-email: fodorad <foauaai@inf.elte.hu>
License-Expression: MIT
License-File: LICENSE
Keywords: bfi-2,personality,questionnaire,vas-f
Classifier: License :: OSI Approved :: MIT License
Classifier: Operating System :: OS Independent
Classifier: Programming Language :: Python :: 3
Requires-Python: >=3.11
Requires-Dist: numpy
